logdash/__init__.py
logdash/constants.py
logdash/core.py
logdash/internal.py
logdash/logger.py
logdash/metrics/__init__.py
logdash/metrics/base.py
logdash/metrics/factory.py
logdash/metrics/impl.py
logdash/metrics/noop.py
logdash/sync/__init__.py
logdash/sync/base.py
logdash/sync/factory.py
logdash/sync/http.py
logdash/sync/noop.py
logdash-1.1.0.dist-info/licenses/LICENSE
logdash-1.1.0.dist-info/METADATA
logdash-1.1.0.dist-info/WHEEL
logdash-1.1.0.dist-info/top_level.txt
logdash-1.1.0.dist-info/RECORD
